fagfunksjoner/__init__.py
fagfunksjoner/api/__init__.py
fagfunksjoner/api/statistikkregisteret.py
fagfunksjoner/api/valuta.py
fagfunksjoner/dapla/__init__.py
fagfunksjoner/dapla/gsm.py
fagfunksjoner/dapla/standards/__init__.py
fagfunksjoner/dapla/standards/time_functions.py
fagfunksjoner/data/__init__.py
fagfunksjoner/data/datadok_extract.py
fagfunksjoner/data/dicts.py
fagfunksjoner/data/klass_xml.py
fagfunksjoner/data/pandas_combinations.py
fagfunksjoner/data/pandas_dtypes.py
fagfunksjoner/data/pyarrow.py
fagfunksjoner/data/round_ssb.py
fagfunksjoner/data/view_dataframe.py
fagfunksjoner/fagfunksjoner_logger.py
fagfunksjoner/formats/__init__.py
fagfunksjoner/formats/formats.py
fagfunksjoner/log/__init__.py
fagfunksjoner/log/statlogger.py
fagfunksjoner/paths/__init__.py
fagfunksjoner/paths/git.py
fagfunksjoner/paths/project_root.py
fagfunksjoner/paths/user.py
fagfunksjoner/paths/versions.py
fagfunksjoner/prodsone/__init__.py
fagfunksjoner/prodsone/check_env.py
fagfunksjoner/prodsone/dynarev.py
fagfunksjoner/prodsone/oradb.py
fagfunksjoner/prodsone/saspy_ssb.py
fagfunksjoner/py.typed
ssb_fagfunksjoner-1.1.3.dist-info/METADATA
ssb_fagfunksjoner-1.1.3.dist-info/WHEEL
ssb_fagfunksjoner-1.1.3.dist-info/entry_points.txt
ssb_fagfunksjoner-1.1.3.dist-info/licenses/LICENSE
ssb_fagfunksjoner-1.1.3.dist-info/RECORD
