Metadata-Version: 2.4
Name: ssb-fagfunksjoner
Version: 1.1.3
Summary: Fellesfunksjoner for ssb i Python
License-Expression: MIT
License-File: LICENSE
Author: SSB-pythonistas
Author-email: ssb-pythonistas@ssb.no
Requires-Python: >=3.10
Classifier: Development Status :: 4 - Beta
Classifier: Programming Language :: Python :: 3
Classifier: Programming Language :: Python :: 3.10
Classifier: Programming Language :: Python :: 3.11
Classifier: Programming Language :: Python :: 3.12
Classifier: Programming Language :: Python :: 3.13
Classifier: Programming Language :: Python :: 3.14
Requires-Dist: colorama (>=0.4.6)
Requires-Dist: colorlog (>=6.9.0)
Requires-Dist: dapla-auth-client (>=1.2.5)
Requires-Dist: dapla-toolbelt (>=4.0.0)
Requires-Dist: google-cloud-secret-manager (>=2.25.0)
Requires-Dist: ipython (>=8.37.0)
Requires-Dist: ipywidgets (>=8.1.1)
Requires-Dist: numpy (>=2.2)
Requires-Dist: oracledb (>=2.3.0)
Requires-Dist: pandas (>=2.0.0)
Requires-Dist: pyarrow (>=14.0.1)
Requires-Dist: python-dateutil (>=2.9.0)
Requires-Dist: requests (>=2.31.0)
Requires-Dist: saspy (>=5.2.1)
Requires-Dist: toml (>=0.10.2)
Project-URL: Changelog, https://github.com/statisticsnorway/ssb-fagfunksjoner/releases
Project-URL: Documentation, https://statisticsnorway.github.io/ssb-fagfunksjoner
Project-URL: Homepage, https://github.com/statisticsnorway/ssb-fagfunksjoner
Project-URL: Repository, https://github.com/statisticsnorway/ssb-fagfunksjoner
